pyweatherget/__init__.py
pyweatherget/pyweatherget.py
pyweatherget-0.0.1.dist-info/LICENSE
pyweatherget-0.0.1.dist-info/METADATA
pyweatherget-0.0.1.dist-info/WHEEL
pyweatherget-0.0.1.dist-info/top_level.txt
pyweatherget-0.0.1.dist-info/RECORD
